pydantic_api/notion/sdk/__init__.py
pydantic_api/notion/sdk/client.py
pydantic_api/notion/sdk/endpoints/__init__.py
pydantic_api/notion/sdk/endpoints/base.py
pydantic_api/notion/sdk/endpoints/blocks.py
pydantic_api/notion/sdk/endpoints/comments.py
pydantic_api/notion/sdk/endpoints/databases.py
pydantic_api/notion/sdk/endpoints/pages.py
pydantic_api/notion/sdk/endpoints/search.py
pydantic_api/notion/sdk/endpoints/users.py
pydantic_api/notion/sdk/exception.py
pydantic_api/notion/sdk/tools/__init__.py
pydantic_api/notion/sdk/tools/notion_database_linker.py
pydantic_api_sdk_notion-0.0.37.dist-info/METADATA
pydantic_api_sdk_notion-0.0.37.dist-info/WHEEL
pydantic_api_sdk_notion-0.0.37.dist-info/licenses/LICENSE
pydantic_api_sdk_notion-0.0.37.dist-info/RECORD
