Metadata-Version: 2.4
Name: pydantic-api-sdk-notion
Version: 0.0.37
Summary: Type Safe SDK For Notion API
License: MIT
License-File: LICENSE
Keywords: notion,pydantic,api,type-safe
Author: stevieflyer
Requires-Python: >=3.12,<4.0
Classifier: Development Status :: 3 - Alpha
Classifier: Intended Audience :: Developers
Classifier: License :: OSI Approved :: MIT License
Classifier: Programming Language :: Python :: 3
Classifier: Programming Language :: Python :: 3.12
Classifier: Programming Language :: Python :: 3.13
Classifier: Programming Language :: Python :: 3.14
Classifier: Programming Language :: Python :: 3.10
Classifier: Programming Language :: Python :: 3.11
Classifier: Topic :: Software Development :: Libraries
Requires-Dist: notion-client (>=2.2.1,<3.0.0)
Requires-Dist: pydantic-api-models-notion (>=0.0.23,<0.0.24)
Project-URL: Homepage, https://github.com/stevieflyer/pydantic-api-sdk-notion
Project-URL: Repository, https://github.com/stevieflyer/pydantic-api-sdk-notion
